flask_shell_ptpython.py
flask_shell_ptpython2-1.0.7.dist-info/AUTHORS
flask_shell_ptpython2-1.0.7.dist-info/LICENSE
flask_shell_ptpython2-1.0.7.dist-info/METADATA
flask_shell_ptpython2-1.0.7.dist-info/WHEEL
flask_shell_ptpython2-1.0.7.dist-info/entry_points.txt
flask_shell_ptpython2-1.0.7.dist-info/top_level.txt
flask_shell_ptpython2-1.0.7.dist-info/RECORD
