Metadata-Version: 2.1
Name: flask-shell-ptpython2
Version: 1.0.7
Summary: Replace the default ``flask shell`` command with a similar one running PTPython.
Home-page: https://github.com/azmeuk/flask-shell-ptpython
Author: Jacopo Notarstefano
Author-email: jacopo.notarstefano@gmail.com
License: MIT
Platform: any
Classifier: Development Status :: 5 - Production/Stable
Classifier: Environment :: Console
Classifier: Intended Audience :: Developers
Classifier: License :: OSI Approved :: MIT License
Classifier: Operating System :: OS Independent
Classifier: Programming Language :: Python :: 3
Classifier: Programming Language :: Python :: 3.7
Classifier: Programming Language :: Python :: 3.8
Classifier: Programming Language :: Python :: 3.9
Classifier: Programming Language :: Python :: 3.10
Classifier: Programming Language :: Python :: 3.11
Classifier: Programming Language :: Python
License-File: LICENSE
License-File: AUTHORS
Requires-Dist: Flask (>=0.12.2)
Requires-Dist: click (>=6.7)
Requires-Dist: ptpython (>=0.41)
Provides-Extra: all
Provides-Extra: docs
Provides-Extra: tests
